logicgates_design.v
//gatelevel modeling
module logicgates_and_gate_gatelevel(input a, b, output y);
 and(y, a, b);
endmodule

module logicgates_or_gate_gatelevel(input a, b, output y);
 or(y, a, b);
endmodule

module logicgates_not_gate_gatelevel(input a, b, output y);
 not(y, a);
endmodule

module logicgates_nor_gate_gatelevel(input a, b, output y);
 nor(y, a, b);
endmodule

module logicgates_nand_gate_gatelevel(input a, b, output y);
 nand(y, a, b);
endmodule

module logicgates_xor_gate_gatelevel(input a, b, output y);
 xor(y, a, b);
endmodule

module logicgates_xnor_gate_gatelevel(input a, input b, output y);
 xnor(y, a, b);
endmodule

//dataflow modeling
module logicgates_and_gate_dataflow(input a, input b, output y);
 assign y = a & b;
endmodule

module logicgates_or_gate_dataflow(input a, input b, output y);
 assign y = a | b;
endmodule

module logicgates_not_gate_dataflow(input a, input b, output y);
 assign y = ~a;
endmodule

module logicgates_nor_gate_dataflow(input a, input b, output y);
 assign y = ~(a | b);
endmodule

module logicgates_nand_gate_dataflow(input a, input b, output y);
 assign y = ~(a & b);
endmodule

module logicgates_xor_gate_dataflow(input a, input b, output y);
 assign y = a ^ b;
endmodule
 
module logicgates_xnor_gate_dataflow(input a, input b, output y);
 assign y = ~(a^b);
endmodule

//Behavioral modeling
module logicgates_and_gate_behavioral(input a, input b, output reg y);
 always @(*)
  y = a & b;
endmodule

module logicgates_or_gate_behavioral(input a, input b, output reg y);
 always @(*)
  y = a | b;
endmodule

module logicgates_not_gate_behavioral(input a, input b, output reg y);
 always @(*)
  y = ~a;
endmodule

module logicgates_nor_gate_behavioral(input a, input b, output reg y);
 always @(*)
  y = ~(a | b);
endmodule

module logicgates_nand_gate_behavioral(input a, input b, output reg y);
 always @(*)
  y = a ^ b;
endmodule

module logicgates_xnor_gate_behavioral(input a, input b, output reg y);
 always @(*)
  y = ~(a ^ b);
endmodule

logicgates_tb.v
`include "logicgates_design.v"
module tb;
reg a, b;
wire y_and_g, y_or_g,  y_not_g,  y_nor_g,  y_nand_g,  y_xor_g,  y_xnor_g;
wire y_and_d, y_or_d,  y_not_d,  y_nor_d,  y_nand_d,  y_xor_d,  y_xnor_d;
wire y_and_b, y_or_b,  y_not_b,  y_nor_b,  y_nand_b,  y_xor_b,  y_xnor_b;
//gatelevel instances
logicgates_and_gate_gatelevel u1(.a(a), .b(b), .y(y_and_g));
logicgates_or_gate_gatelevel u2(.a(a), .b(b), .y(y_or_g));
logicgates_not_gate_gatelevel u3(.a(a), .b(b), .y(y_not_g));
logicgates_nor_gate_gatelevel u4(.a(a), .b(b), .y(y_nor_g));
logicgates_nand_gate_gatelevel u5(.a(a), .b(b), .y(y_nand_g));
logicgates_xor_gate_gatelevel u6(.a(a), .b(b), .y(y_xor_g));
logicgates_xnor_gate_gatelevel u7(.a(a), .b(b), .y(y_xnor_g));
//Dataflow instances
logicgates_and_gate_dataflow u8(.a(a), .b(b), .y(y_and_d));
logicgates_or_gate_dataflow u9(.a(a), .b(b), .y(y_or_d));
logicgates_not_gate_dataflow u10(.a(a), .b(b), .y(y_not_d));
logicgates_nor_gate_dataflow u11(.a(a), .b(b), .y(y_nor_d));
logicgates_nand_gate_dataflow u12(.a(a), .b(b), .y(y_nand_d));
logicgates_xor_gate_dataflow u13(.a(a), .b(b), .y(y_xor_d));
logicgates_xnor_gate_dataflow u14(.a(a), .b(b), .y(y_xnor_d));
//Behavioral instances
logicgates_and_gate_dataflow u15(.a(a), .b(b), .y(y_and_b));
logicgates_or_gate_dataflow u16(.a(a), .b(b), .y(y_or_b));
logicgates_not_gate_dataflow u17(.a(a), .b(b), .y(y_not_b));
logicgates_nor_gate_dataflow u18(.a(a), .b(b), .y(y_nor_b));
logicgates_nand_gate_dataflow u19(.a(a), .b(b), .y(y_nand_b));
logicgates_xor_gate_dataflow u20(.a(a), .b(b), .y(y_xor_b));
logicgates_xnor_gate_dataflow u21(.a(a), .b(b), .y(y_xnor_b));
initial begin
 $display("A B | And_b d g |or_b d g | not_b d g |nor_b d g | nand_b d g |xor_b d g | xnor_b d g");
 repeat(100)begin
  {a,b}=$random;#10;
  $display("%b %b |%b %b %b |%b %b %b |%b %b | %b %b %b |%b %b %b |%b %b %b|%b %b %b", a, b, 
  y_and_g, y_and_d, y_and_b,
  y_or_g, y_or_d, y_or_b,
  y_not_g, y_not_d, y_not_b,
  y_nor_g, y_nor_d, y_nor_b,
  y_nand_g, y_nand_d, y_nand_b,
  y_xor_g, y_xor_d, y_xor_b,
  y_xnor_g, y_xnor_d, y_xnor_b);
end
end
initial begin
 $dumpfile("dump.vcd");
 $dumpvars(1,tb);
end
endmodule

dump.vcd
$date
	Tue Sep 16 15:42:41 2025
$end
$version
	ModelSim Version 2020.1
$end
$timescale
	1ps
$end

$scope module tb $end
$var reg 1 ! a $end
$var reg 1 " b $end
$var wire 1 # y_and_g $end
$var wire 1 $ y_or_g $end
$var wire 1 % y_not_g $end
$var wire 1 & y_nor_g $end
$var wire 1 ' y_nand_g $end
$var wire 1 ( y_xor_g $end
$var wire 1 ) y_xnor_g $end
$var wire 1 * y_and_d $end
$var wire 1 + y_or_d $end
$var wire 1 , y_not_d $end
$var wire 1 - y_nor_d $end
$var wire 1 . y_nand_d $end
$var wire 1 / y_xor_d $end
$var wire 1 0 y_xnor_d $end
$var wire 1 1 y_and_b $end
$var wire 1 2 y_or_b $end
$var wire 1 3 y_not_b $end
$var wire 1 4 y_nor_b $end
$var wire 1 5 y_nand_b $end
$var wire 1 6 y_xor_b $end
$var wire 1 7 y_xnor_b $end
$upscope $end
$enddefinitions $end
#0
$dumpvars
0!
0"
0#
0$
1%
1&
1'
0(
1)
0*
0+
1,
1-
1.
0/
10
01
02
13
14
15
06
17
$end
#10
1"
07
16
04
12
00
1/
0-
1+
1$
0&
1(
0)
#30
1!
17
06
05
03
11
10
0/
0.
0,
1*
1#
0%
0'
0(
1)
#40
0!
07
16
15
13
01
00
1/
1.
1,
0*
0#
1%
1'
1(
0)
#70
0"
1!
03
0,
0%
#80
1"
0!
13
1,
1%
#100
0"
1!
03
0,
0%
#110
1"
0!
13
1,
1%
#130
0"
17
06
14
02
10
0/
1-
0+
0$
1&
0(
1)
#140
1"
07
16
04
12
00
1/
0-
1+
1$
0&
1(
0)
#150
0"
1!
03
0,
0%
#160
1"
0!
13
1,
1%
#170
0"
1!
03
0,
0%
#180
1"
0!
13
1,
1%
#190
1!
17
06
05
03
11
10
0/
0.
0,
1*
1#
0%
0'
0(
1)
#200
0"
07
16
15
01
00
1/
1.
0*
0#
1'
1(
0)
#210
1"
17
06
05
11
10
0/
0.
1*
1#
0'
0(
1)
#220
0"
07
16
15
01
00
1/
1.
0*
0#
1'
1(
0)
#240
0!
17
06
14
13
02
10
0/
1-
1,
0+
0$
1%
1&
0(
1)
#250
1"
07
16
04
12
00
1/
0-
1+
1$
0&
1(
0)
#260
0"
17
06
14
02
10
0/
1-
0+
0$
1&
0(
1)
#270
1"
07
16
04
12
00
1/
0-
1+
1$
0&
1(
0)
#300
1!
17
06
05
03
11
10
0/
0.
0,
1*
1#
0%
0'
0(
1)
#310
0"
07
16
15
01
00
1/
1.
0*
0#
1'
1(
0)
#320
0!
17
06
14
13
02
10
0/
1-
1,
0+
0$
1%
1&
0(
1)
#340
1!
07
16
04
03
12
00
1/
0-
0,
1+
1$
0%
0&
1(
0)
#350
1"
0!
13
1,
1%
#360
0"
1!
03
0,
0%
#370
1"
17
06
05
11
10
0/
0.
1*
1#
0'
0(
1)
#380
0!
07
16
15
13
01
00
1/
1.
1,
0*
0#
1%
1'
1(
0)
#390
1!
17
06
05
03
11
10
0/
0.
0,
1*
1#
0%
0'
0(
1)
#410
0!
07
16
15
13
01
00
1/
1.
1,
0*
0#
1%
1'
1(
0)
#420
0"
1!
03
0,
0%
#440
1"
0!
13
1,
1%
#450
1!
17
06
05
03
11
10
0/
0.
0,
1*
1#
0%
0'
0(
1)
#470
0"
07
16
15
01
00
1/
1.
0*
0#
1'
1(
0)
#490
0!
17
06
14
13
02
10
0/
1-
1,
0+
0$
1%
1&
0(
1)
#500
1!
07
16
04
03
12
00
1/
0-
0,
1+
1$
0%
0&
1(
0)
#520
1"
0!
13
1,
1%
#530
0"
17
06
14
02
10
0/
1-
0+
0$
1&
0(
1)
#550
1"
07
16
04
12
00
1/
0-
1+
1$
0&
1(
0)
#560
1!
17
06
05
03
11
10
0/
0.
0,
1*
1#
0%
0'
0(
1)
#570
0"
07
16
15
01
00
1/
1.
0*
0#
1'
1(
0)
#600
0!
17
06
14
13
02
10
0/
1-
1,
0+
0$
1%
1&
0(
1)
#610
1!
07
16
04
03
12
00
1/
0-
0,
1+
1$
0%
0&
1(
0)
#620
1"
17
06
05
11
10
0/
0.
1*
1#
0'
0(
1)
#630
0!
07
16
15
13
01
00
1/
1.
1,
0*
0#
1%
1'
1(
0)
#650
1!
17
06
05
03
11
10
0/
0.
0,
1*
1#
0%
0'
0(
1)
#670
0"
07
16
15
01
00
1/
1.
0*
0#
1'
1(
0)
#690
1"
0!
13
1,
1%
#720
0"
1!
03
0,
0%
#730
0!
17
06
14
13
02
10
0/
1-
1,
0+
0$
1%
1&
0(
1)
#740
1"
1!
05
03
11
0.
0,
1*
04
12
0-
1+
1#
1$
0&
0'
0%
#760
0"
0!
14
13
02
1-
1,
0+
15
01
1.
0*
0#
0$
1&
1'
1%
#770
1"
1!
05
03
11
0.
0,
1*
04
12
0-
1+
1#
1$
0&
0'
0%
#790
0"
0!
14
13
02
1-
1,
0+
15
01
1.
0*
0#
0$
1&
1'
1%
#800
1"
1!
05
03
11
0.
0,
1*
04
12
0-
1+
1#
1$
0&
0'
0%
#810
0!
07
16
15
13
01
00
1/
1.
1,
0*
0#
1%
1'
1(
0)
#830
0"
17
06
14
02
10
0/
1-
0+
0$
1&
0(
1)
#840
1"
1!
05
03
11
0.
0,
1*
04
12
0-
1+
1#
1$
0&
0'
0%
#850
0!
07
16
15
13
01
00
1/
1.
1,
0*
0#
1%
1'
1(
0)
#860
0"
1!
03
0,
0%
#870
0!
17
06
14
13
02
10
0/
1-
1,
0+
0$
1%
1&
0(
1)
#880
1!
07
16
04
03
12
00
1/
0-
0,
1+
1$
0%
0&
1(
0)
#890
0!
17
06
14
13
02
10
0/
1-
1,
0+
0$
1%
1&
0(
1)
#900
1"
1!
05
03
11
0.
0,
1*
04
12
0-
1+
1#
1$
0&
0'
0%
#910
0!
07
16
15
13
01
00
1/
1.
1,
0*
0#
1%
1'
1(
0)
#920
0"
1!
03
0,
0%
#940
1"
0!
13
1,
1%
#960
1!
17
06
05
03
11
10
0/
0.
0,
1*
1#
0%
0'
0(
1)
#980
0!
07
16
15
13
01
00
1/
1.
1,
0*
0#
1%
1'
1(
0)
#990
0"
17
06
14
02
10
0/
1-
0+
0$
1&
0(
1)
